{
"skeleton": {
	"hash": "UAN3D/eXj88",
	"spine": "4.2.35",
	"x": -32,
	"y": -23.21,
	"width": 64,
	"height": 64,
	"images": "../tiles/temple/fire/",
	"audio": ""
},
"bones": [
	{ "name": "root", "scaleX": 2, "scaleY": 2 },
	{ "name": "middle", "parent": "root" }
],
"slots": [
	{ "name": "01", "bone": "middle", "attachment": "01" },
	{ "name": "hitbox", "bone": "middle", "attachment": "hitbox" }
],
"skins": [
	{
		"name": "default",
		"attachments": {
			"01": {
				"01": { "y": 4.39, "width": 32, "height": 32 },
				"02": { "y": 4.39, "width": 32, "height": 32 },
				"03": { "y": 4.39, "width": 32, "height": 32 },
				"04": { "y": 4.39, "width": 32, "height": 32 },
				"05": { "y": 4.39, "width": 32, "height": 32 }
			},
			"hitbox": {
				"hitbox": {
					"type": "boundingbox",
					"vertexCount": 4,
					"vertices": [ -8.01, 5.62, 6.94, 5.65, 6.96, -5.77, -8.01, -5.7 ]
				}
			}
		}
	}
],
"animations": {
	"idle": {
		"slots": {
			"01": {
				"attachment": [
					{ "name": "01" },
					{ "time": 0.1667, "name": "02" },
					{ "time": 0.3333, "name": "03" },
					{ "time": 0.5, "name": "04" },
					{ "time": 0.6667, "name": "05" },
					{ "time": 0.8, "name": "05" }
				]
			}
		}
	}
}
}